labpype
