Metadata-Version: 1.1
Name: LabPype
Version: 0.7.3
Summary: A Framework for Creating Pipeline Software
Home-page: https://github.com/NCBI-Hackathons/LabPype
Author: Yadi Zhou
Author-email: yadizhou90@gmail.com
License: GPL-3.0
Keywords: Pipeline Workflow Widget Bioinformatics GUI
Platform: UNKNOWN
Classifier: Development Status :: 3 - Alpha
Classifier: Environment :: Win32 (MS Windows)
Classifier: Environment :: X11 Applications :: GTK
Classifier: Environment :: MacOS X :: Cocoa
Classifier: Operating System :: Microsoft :: Windows :: Windows 10
Classifier: Operating System :: Microsoft :: Windows :: Windows 7
Classifier: Operating System :: POSIX :: Linux
Classifier: Operating System :: MacOS :: MacOS X
Classifier: Intended Audience :: Developers
Classifier: Intended Audience :: Education
Classifier: Intended Audience :: End Users/Desktop
Classifier: Intended Audience :: Science/Research
Classifier: Topic :: Education
Classifier: Topic :: Scientific/Engineering :: Bio-Informatics
Classifier: Topic :: Software Development :: User Interfaces
Classifier: Topic :: Software Development :: Widget Sets
Classifier: Programming Language :: Python :: 3.5
Classifier: Programming Language :: Python :: 3.6
